colony/__init__.py
colony/base.py
colony/blueprints.py
colony/client.py
colony/constants.py
colony/exceptions.py
colony/sandboxes.py
colony/session.py
colony/shell.py
colony/utils.py
colony/branch/__init__.py
colony/branch/branch_context.py
colony/branch/branch_utils.py
colony/commands/__init__.py
colony/commands/base.py
colony/commands/bp.py
colony/commands/configure.py
colony/commands/sb.py
colony/models/__init__.py
colony/models/connection.py
colony/parsers/__init__.py
colony/parsers/command_input_parsers.py
colony/parsers/command_input_validators.py
colony/parsers/global_input_parser.py
colony/services/__init__.py
colony/services/config.py
colony/services/connection.py
colony/services/sb_naming.py
colony/services/version.py
colony/services/waiter.py
colony/view/__init__.py
colony/view/configure_list_view.py
colony/view/view_helper.py
colony_cli-1.3.0b0.dist-info/LICENSE
colony_cli-1.3.0b0.dist-info/METADATA
colony_cli-1.3.0b0.dist-info/WHEEL
colony_cli-1.3.0b0.dist-info/entry_points.txt
colony_cli-1.3.0b0.dist-info/top_level.txt
colony_cli-1.3.0b0.dist-info/RECORD
